setup.py
google_seo_analyzer.egg-info/PKG-INFO
google_seo_analyzer.egg-info/SOURCES.txt
google_seo_analyzer.egg-info/dependency_links.txt
google_seo_analyzer.egg-info/requires.txt
google_seo_analyzer.egg-info/top_level.txt
seo_analyzer/__init__.py
seo_analyzer/seo_analyzer.py