Metadata-Version: 1.0
Name: google-seo-analyzer
Version: 0.1.1
Summary: This simple script parses Google Web Master Tools report and analyzes results.
Home-page: https://github.com/victorpantoja/google-seo-analyzer
Author: Victor Pantoja
Author-email: victor.pantoja@gmail.com
License: MIT
Keywords: gogole seo analyzer crawler report
Platform: UNKNOWN
Classifier: Development Status :: 4 - Beta
Classifier: Intended Audience :: Developers
Classifier: Programming Language :: Python
